grammar_utils-0.1.3.dist-info/METADATA
grammar_utils-0.1.3.dist-info/WHEEL
grammar_utils-0.1.3.dist-info/license_files/LICENSE
grammar_utils/grammars/json/json.y
grammar_utils/grammars/json/json.l
grammar_utils/grammars/__init__.py
grammar_utils/grammars/sparql/sparql.y
grammar_utils/grammars/sparql/sparql.l
grammar_utils/version.py
grammar_utils/constrain/__init__.py
grammar_utils/parse/__init__.py
grammar_utils/__init__.py
grammar_utils/_internal.abi3.so
grammar_utils-0.1.3.dist-info/RECORD
