Metadata-Version: 2.1
Name: grammar-utils
Version: 0.1.3
Classifier: Programming Language :: Rust
Classifier: Programming Language :: Python :: 3
Classifier: Topic :: Software Development :: Libraries
Classifier: Topic :: Text Processing
Classifier: Topic :: Utilities
Requires-Dist: numpy >=1.26
License-File: LICENSE
Summary: Utilities for regex and grammar parsing and constraining
Keywords: nlp,utilities,text,grammar,constraint
Author-email: Sebastian Walter <swalter@cs.uni-freiburg.de>
Requires-Python: >=3.10
Project-URL: Github, https://github.com/bastiscode/grammar-utils
